base_client/__init__.py
base_client/base_client.py
base_client/errors.py
base_client/py.typed
base_client/response.py
base_client-0.1.3.dist-info/WHEEL
base_client-0.1.3.dist-info/METADATA
base_client-0.1.3.dist-info/RECORD
