Metadata-Version: 2.3
Name: base-client
Version: 0.1.3
Summary: Implementation of base client
Keywords: python
Author: community-of-python
Classifier: Typing :: Typed
Classifier: Programming Language :: Python :: 3.10
Classifier: Programming Language :: Python :: 3.11
Classifier: Programming Language :: Python :: 3.12
Classifier: Programming Language :: Python :: 3.13
Requires-Dist: httpx
Requires-Dist: pydantic
Requires-Dist: multidict
Requires-Dist: circuit-breaker-box
Requires-Dist: redis ; extra == 'redis'
Requires-Python: >=3.10, <4
Project-URL: Changelogs, https://github.com/community-of-python/base-client/releases
Project-URL: Issues, https://github.com/community-of-python/base-client/issues
Project-URL: Repository, https://github.com/community-of-python/base-client
Provides-Extra: redis
